LICENSE
MANIFEST.in
README
setup.py
Sauri.egg-info/PKG-INFO
Sauri.egg-info/SOURCES.txt
Sauri.egg-info/dependency_links.txt
Sauri.egg-info/requires.txt
Sauri.egg-info/top_level.txt
sauri/__init__.py
sauri/collector.py
sauri/run_tests.sh
sauri/bin/pub_test.py
sauri/bin/sub_test.py
sauri/cfg/home.yaml
sauri/common/__init__.py
sauri/common/config.py
sauri/common/loginit.py
sauri/messaging/__init__.py
sauri/messaging/broker.py
sauri/messaging/factory.py
sauri/messaging/types.py
sauri/messaging/blocking/__init__.py
sauri/messaging/blocking/amqpbase.py
sauri/messaging/blocking/amqppublisher.py
sauri/messaging/blocking/amqpsubscriber.py
sauri/messaging/blocking/broker.py
sauri/messaging/blocking/factory.py
sauri/messaging/blocking/protocols.py
sauri/messaging/blocking/test/__init__.py
sauri/messaging/blocking/test/testbroker.py
sauri/sensors/__init__.py
sauri/sensors/categories.py
sauri/sensors/factory.py
sauri/sensors/sensor.py
sauri/sensors/temperature/__init__.py
sauri/sensors/temperature/ds18b20.py
sauri/sensors/temperature/factory.py
sauri/sensors/temperature/temperatureSensor.py
sauri/sensors/temperature/types.py
sauri/sensors/temperature/test/__init__.py
sauri/sensors/temperature/test/testds18b20.py
sauri/sensors/temperature/test/testfactory.py
sauri/sensors/temperature/test/testtemperaturesensor.py
sauri/sensors/test/__init__.py
sauri/sensors/test/testfactory.py