Metadata-Version: 1.0
Name: Sauri
Version: 0.2
Summary: UNKNOWN
Home-page: https://github.com/healem/sauri
Author: Mike Healey
Author-email: healem@alum.rpi.edu
License: MIT
Platform: UNKNOWN
